[
  {
    "number": 918,
    "project_path": "Issue918.csproj",
    "project_style": "SDK-style",
    "target_frameworks": [
      "net10.0"
    ],
    "packages": [
      "Microsoft.NET.Test.Sdk=18.0.1",
      "NUnit=4.4.0",
      "coverlet.collector=6.0.4"
    ],
    "update_result": "success",
    "update_output": "[Issue918\\Issue918.csproj]\nDiscovering projects...\r\nAnalyzing project(s)...\r\nAnalyzing dependencies...\r\nNo outdated dependencies were detected\r\nElapsed: 00:00:03.8515027\r\n",
    "update_error": "",
    "restore_result": "success",
    "restore_output": "  Determining projects to restore...\r\n  Restored C:\\repos\\nunit\\nunit3-vs-adapter.issues\\Issue918\\Issue918.csproj (in 497 ms).\r\n",
    "restore_error": "",
    "build_result": "success",
    "build_output": "  Determining projects to restore...\r\n  All projects are up-to-date for restore.\r\n  Issue918 -\u003E C:\\repos\\nunit\\nunit3-vs-adapter.issues\\Issue918\\bin\\Debug\\net10.0\\Issue918.dll\r\n\r\nBuild succeeded.\r\n    0 Warning(s)\r\n    0 Error(s)\r\n\r\nTime Elapsed 00:00:03.38\r\n",
    "build_error": "",
    "test_result": "success",
    "test_output": "=== Issue918\\Issue918.csproj ===\n=== Restore ===\n  Determining projects to restore...\r\n  Restored C:\\repos\\nunit\\nunit3-vs-adapter.issues\\Issue918\\Issue918.csproj (in 497 ms).\r\n\n=== Build ===\n  Determining projects to restore...\r\n  All projects are up-to-date for restore.\r\n  Issue918 -\u003E C:\\repos\\nunit\\nunit3-vs-adapter.issues\\Issue918\\bin\\Debug\\net10.0\\Issue918.dll\r\n\r\nBuild succeeded.\r\n    0 Warning(s)\r\n    0 Error(s)\r\n\r\nTime Elapsed 00:00:03.38\r\n\n=== Test ===\n  Determining projects to restore...\r\n  All projects are up-to-date for restore.\r\n  Issue918 -\u003E C:\\repos\\nunit\\nunit3-vs-adapter.issues\\Issue918\\bin\\Debug\\net10.0\\Issue918.dll\r\nTest run for C:\\repos\\nunit\\nunit3-vs-adapter.issues\\Issue918\\bin\\Debug\\net10.0\\Issue918.dll (.NETCoreApp,Version=v10.0)\r\nVSTest version 18.0.1 (x64)\r\n\r\nStarting test execution, please wait...\r\nA total of 1 test files matched the specified pattern.\r\n\r\nPassed!  - Failed:     0, Passed:     1, Skipped:     0, Total:     1, Duration: 44 ms - Issue918.dll (net10.0)\r\n",
    "test_error": "",
    "test_conclusion": "Success: No regression failure (1 test(s) passed)",
    "runner_scripts": null,
    "runsettings": null,
    "feed": "Stable",
    "runner_expectations": null,
    "last_run": "2026-01-19T21:45:02Z"
  }
]