[
  {
    "number": 1231,
    "project_path": "Issue1231.csproj",
    "project_style": "sdk",
    "target_frameworks": [
      "net10.0"
    ],
    "packages": [
      "coverlet.collector=6.0.4",
      "Microsoft.NET.Test.Sdk=18.0.1",
      "NUnit=4.4.0",
      "NUnit.Analyzers=4.11.2",
      "NUnit3TestAdapter=6.0.0"
    ],
    "update_result": "success",
    "update_output": "[nunit]\nDiscovering projects...\nAnalyzing project(s)...\nAnalyzing dependencies...\nNo outdated dependencies were detected\nElapsed: 00:00:03.2497218\n\n[other]\nDiscovering projects...\nAnalyzing project(s)...\nAnalyzing dependencies...\nNo outdated dependencies were detected\nElapsed: 00:00:03.4205555\n",
    "update_error": "[nunit]\n\n[other]\n",
    "test_result": "success",
    "test_output": "  Determining projects to restore...\n  Restored C:\\repos\\nunit\\nunit3-vs-adapter.issues\\Issue1231\\Issue1231.csproj (in 538 ms).\n  Issue1231 -> C:\\repos\\nunit\\nunit3-vs-adapter.issues\\Issue1231\\bin\\Debug\\net10.0\\Issue1231.dll\nTest run for C:\\repos\\nunit\\nunit3-vs-adapter.issues\\Issue1231\\bin\\Debug\\net10.0\\Issue1231.dll (.NETCoreApp,Version=v10.0)\nVSTest version 18.0.1 (x64)\n\nStarting test execution, please wait...\nA total of 1 test files matched the specified pattern.\n\nPassed!  - Failed:     0, Passed:     4, Skipped:     0, Total:     4, Duration: 54 ms - Issue1231.dll (net10.0)\n",
    "test_error": "",
    "test_conclusion": "Success: No regression failure"
  }
]